[
  {
    "secucode": "002236.SZ",
    "securityCode": "002236",
    "securityInnerCode": "1000007864",
    "securityNameAbbr": "大华股份",
    "holdDate": "2023-08-31 00:00:00",
    "orgCode": "10063640",
    "orgName": "摩根士丹利香港证券有限公司",
    "holdNum": 829184,
    "marketCode": "003",
    "holdSharesRatio": 0.02,
    "holdMarketCap": 17893790.72,
    "closePrice": 21.58,
    "changeRate": 0.7,
    "holdMarketCapone": 1131587.6,
    "holdMarketCapfive": 17867004,
    "holdMarketCapten": 8813946.32,
    "participantCode": "B01274"
  },
  {
    "secucode": "002236.SZ",
    "securityCode": "002236",
    "securityInnerCode": "1000007864",
    "securityNameAbbr": "大华股份",
    "holdDate": "2023-08-30 00:00:00",
    "orgCode": "10063640",
    "orgName": "摩根士丹利香港证券有限公司",
    "holdNum": 782184,
    "marketCode": "003",
    "holdSharesRatio": 0.02,
    "holdMarketCap": 16762203.12,
    "closePrice": 21.43,
    "changeRate": 0.0934,
    "holdMarketCapone": 7440631.68,
    "holdMarketCapfive": 16693866.52,
    "holdMarketCapten": 13111306.12,
    "participantCode": "B01274"
  },
  {
    "secucode": "002236.SZ",
    "securityCode": "002236",
    "securityInnerCode": "1000007864",
    "securityNameAbbr": "大华股份",
    "holdDate": "2023-08-29 00:00:00",
    "orgCode": "10063640",
    "orgName": "摩根士丹利香港证券有限公司",
    "holdNum": 435384,
    "marketCode": "003",
    "holdSharesRatio": 0.01,
    "holdMarketCap": 9321571.44,
    "closePrice": 21.41,
    "changeRate": 5.9377,
    "holdMarketCapone": -2950627.7,
    "holdMarketCapfive": 8008487.64,
    "holdMarketCapten": 5416961.14,
    "participantCode": "B01274"
  },
  {
    "secucode": "002236.SZ",
    "securityCode": "002236",
    "securityInnerCode": "1000007864",
    "securityNameAbbr": "大华股份",
    "holdDate": "2023-08-28 00:00:00",
    "orgCode": "10063640",
    "orgName": "摩根士丹利香港证券有限公司",
    "holdNum": 607234,
    "marketCode": "003",
    "holdSharesRatio": 0.01,
    "holdMarketCap": 12272199.14,
    "closePrice": 20.21,
    "changeRate": 4.1753,
    "holdMarketCapone": 11544039.54,
    "holdMarketCapfive": 2646751.88,
    "holdMarketCapten": 1964650.47,
    "participantCode": "B01274"
  },
  {
    "secucode": "002236.SZ",
    "securityCode": "002236",
    "securityInnerCode": "1000007864",
    "securityNameAbbr": "大华股份",
    "holdDate": "2023-08-25 00:00:00",
    "orgCode": "10063640",
    "orgName": "摩根士丹利香港证券有限公司",
    "holdNum": 37534,
    "marketCode": "003",
    "holdSharesRatio": 0,
    "holdMarketCap": 728159.6,
    "closePrice": 19.4,
    "changeRate": -3.3865,
    "holdMarketCapone": 701372.88,
    "holdMarketCapfive": -5582299.48,
    "holdMarketCapten": -2254036.4,
    "participantCode": "B01274"
  },
  {
    "secucode": "002236.SZ",
    "securityCode": "002236",
    "securityInnerCode": "1000007864",
    "securityNameAbbr": "大华股份",
    "holdDate": "2023-08-24 00:00:00",
    "orgCode": "10063640",
    "orgName": "摩根士丹利香港证券有限公司",
    "holdNum": 1334,
    "marketCode": "003",
    "holdSharesRatio": 0,
    "holdMarketCap": 26786.72,
    "closePrice": 20.08,
    "changeRate": 0.9045,
    "holdMarketCapone": -41549.88,
    "holdMarketCapfive": -9053057.68,
    "holdMarketCapten": -2899232.29,
    "participantCode": "B01274"
  },
  {
    "secucode": "002236.SZ",
    "securityCode": "002236",
    "securityInnerCode": "1000007864",
    "securityNameAbbr": "大华股份",
    "holdDate": "2023-08-23 00:00:00",
    "orgCode": "10063640",
    "orgName": "摩根士丹利香港证券有限公司",
    "holdNum": 3434,
    "marketCode": "003",
    "holdSharesRatio": 0,
    "holdMarketCap": 68336.6,
    "closePrice": 19.9,
    "changeRate": -3.8647,
    "holdMarketCapone": -1244747.2,
    "holdMarketCapfive": -3582560.4,
    "holdMarketCapten": -26759938.41,
    "participantCode": "B01274"
  },
  {
    "secucode": "002236.SZ",
    "securityCode": "002236",
    "securityInnerCode": "1000007864",
    "securityNameAbbr": "大华股份",
    "holdDate": "2023-08-22 00:00:00",
    "orgCode": "10063640",
    "orgName": "摩根士丹利香港证券有限公司",
    "holdNum": 63434,
    "marketCode": "003",
    "holdSharesRatio": 0,
    "holdMarketCap": 1313083.8,
    "closePrice": 20.7,
    "changeRate": 4.0724,
    "holdMarketCapone": -8312363.46,
    "holdMarketCapfive": -2591526.5,
    "holdMarketCapten": -29282968.2,
    "participantCode": "B01274"
  },
  {
    "secucode": "002236.SZ",
    "securityCode": "002236",
    "securityInnerCode": "1000007864",
    "securityNameAbbr": "大华股份",
    "holdDate": "2023-08-21 00:00:00",
    "orgCode": "10063640",
    "orgName": "摩根士丹利香港证券有限公司",
    "holdNum": 483934,
    "marketCode": "003",
    "holdSharesRatio": 0.01,
    "holdMarketCap": 9625447.26,
    "closePrice": 19.89,
    "changeRate": 1.3761,
    "holdMarketCapone": 3314988.18,
    "holdMarketCapfive": -682101.41,
    "holdMarketCapten": -24974887.74,
    "participantCode": "B01274"
  },
  {
    "secucode": "002236.SZ",
    "securityCode": "002236",
    "securityInnerCode": "1000007864",
    "securityNameAbbr": "大华股份",
    "holdDate": "2023-08-18 00:00:00",
    "orgCode": "10063640",
    "orgName": "摩根士丹利香港证券有限公司",
    "holdNum": 321634,
    "marketCode": "003",
    "holdSharesRatio": 0,
    "holdMarketCap": 6310459.08,
    "closePrice": 19.62,
    "changeRate": -0.9091,
    "holdMarketCapone": -2769385.32,
    "holdMarketCapfive": 3328263.08,
    "holdMarketCapten": -8679565.92,
    "participantCode": "B01274"
  },
  {
    "secucode": "002236.SZ",
    "securityCode": "002236",
    "securityInnerCode": "1000007864",
    "securityNameAbbr": "大华股份",
    "holdDate": "2023-08-17 00:00:00",
    "orgCode": "10063640",
    "orgName": "摩根士丹利香港证券有限公司",
    "holdNum": 458578,
    "marketCode": "003",
    "holdSharesRatio": 0.01,
    "holdMarketCap": 9079844.4,
    "closePrice": 19.8,
    "changeRate": 1.9043,
    "holdMarketCapone": 5428947.4,
    "holdMarketCapfive": 6153825.39,
    "holdMarketCapten": 6373424.4,
    "participantCode": "B01274"
  },
  {
    "secucode": "002236.SZ",
    "securityCode": "002236",
    "securityInnerCode": "1000007864",
    "securityNameAbbr": "大华股份",
    "holdDate": "2023-08-16 00:00:00",
    "orgCode": "10063640",
    "orgName": "摩根士丹利香港证券有限公司",
    "holdNum": 187900,
    "marketCode": "003",
    "holdSharesRatio": 0,
    "holdMarketCap": 3650897,
    "closePrice": 19.43,
    "changeRate": -4.8482,
    "holdMarketCapone": -253713.3,
    "holdMarketCapfive": -23177378.01,
    "holdMarketCapten": -9240492,
    "participantCode": "B01274"
  },
  {
    "secucode": "002236.SZ",
    "securityCode": "002236",
    "securityInnerCode": "1000007864",
    "securityNameAbbr": "大华股份",
    "holdDate": "2023-08-15 00:00:00",
    "orgCode": "10063640",
    "orgName": "摩根士丹利香港证券有限公司",
    "holdNum": 191215,
    "marketCode": "003",
    "holdSharesRatio": 0,
    "holdMarketCap": 3904610.3,
    "closePrice": 20.42,
    "changeRate": -1.6851,
    "holdMarketCapone": -6402938.37,
    "holdMarketCapfive": -26691441.7,
    "holdMarketCapten": -17721085.7,
    "participantCode": "B01274"
  },
  {
    "secucode": "002236.SZ",
    "securityCode": "002236",
    "securityInnerCode": "1000007864",
    "securityNameAbbr": "大华股份",
    "holdDate": "2023-08-14 00:00:00",
    "orgCode": "10063640",
    "orgName": "摩根士丹利香港证券有限公司",
    "holdNum": 496271,
    "marketCode": "003",
    "holdSharesRatio": 0.01,
    "holdMarketCap": 10307548.67,
    "closePrice": 20.77,
    "changeRate": 1.6145,
    "holdMarketCapone": 7325352.67,
    "holdMarketCapfive": -24292786.33,
    "holdMarketCapten": -9105031.33,
    "participantCode": "B01274"
  },
  {
    "secucode": "002236.SZ",
    "securityCode": "002236",
    "securityInnerCode": "1000007864",
    "securityNameAbbr": "大华股份",
    "holdDate": "2023-08-11 00:00:00",
    "orgCode": "10063640",
    "orgName": "摩根士丹利香港证券有限公司",
    "holdNum": 145900,
    "marketCode": "003",
    "holdSharesRatio": 0,
    "holdMarketCap": 2982196,
    "closePrice": 20.44,
    "changeRate": -3.2655,
    "holdMarketCapone": 56176.99,
    "holdMarketCapfive": -12007829,
    "holdMarketCapten": 1345396,
    "participantCode": "B01274"
  },
  {
    "secucode": "002236.SZ",
    "securityCode": "002236",
    "securityInnerCode": "1000007864",
    "securityNameAbbr": "大华股份",
    "holdDate": "2023-08-10 00:00:00",
    "orgCode": "10063640",
    "orgName": "摩根士丹利香港证券有限公司",
    "holdNum": 138477,
    "marketCode": "003",
    "holdSharesRatio": 0,
    "holdMarketCap": 2926019.01,
    "closePrice": 21.13,
    "changeRate": 0,
    "holdMarketCapone": -23902256,
    "holdMarketCapfive": 219599.01,
    "holdMarketCapten": 1917504.01,
    "participantCode": "B01274"
  },
  {
    "secucode": "002236.SZ",
    "securityCode": "002236",
    "securityInnerCode": "1000007864",
    "securityNameAbbr": "大华股份",
    "holdDate": "2023-08-09 00:00:00",
    "orgCode": "10063640",
    "orgName": "摩根士丹利香港证券有限公司",
    "holdNum": 1269677,
    "marketCode": "003",
    "holdSharesRatio": 0.03,
    "holdMarketCap": 26828275.01,
    "closePrice": 21.13,
    "changeRate": -3.516,
    "holdMarketCapone": -3767776.99,
    "holdMarketCapfive": 13936886.01,
    "holdMarketCapten": 25080529.01,
    "participantCode": "B01274"
  },
  {
    "secucode": "002236.SZ",
    "securityCode": "002236",
    "securityInnerCode": "1000007864",
    "securityNameAbbr": "大华股份",
    "holdDate": "2023-08-08 00:00:00",
    "orgCode": "10063640",
    "orgName": "摩根士丹利香港证券有限公司",
    "holdNum": 1397080,
    "marketCode": "003",
    "holdSharesRatio": 0.04,
    "holdMarketCap": 30596052,
    "closePrice": 21.9,
    "changeRate": -1.9257,
    "holdMarketCapone": -4004283,
    "holdMarketCapfive": 8970356,
    "holdMarketCapten": 24068485.2,
    "participantCode": "B01274"
  },
  {
    "secucode": "002236.SZ",
    "securityCode": "002236",
    "securityInnerCode": "1000007864",
    "securityNameAbbr": "大华股份",
    "holdDate": "2023-08-07 00:00:00",
    "orgCode": "10063640",
    "orgName": "摩根士丹利香港证券有限公司",
    "holdNum": 1549500,
    "marketCode": "003",
    "holdSharesRatio": 0.04,
    "holdMarketCap": 34600335,
    "closePrice": 22.33,
    "changeRate": 0.1795,
    "holdMarketCapone": 19610310,
    "holdMarketCapfive": 15187755,
    "holdMarketCapten": 31670910,
    "participantCode": "B01274"
  },
  {
    "secucode": "002236.SZ",
    "securityCode": "002236",
    "securityInnerCode": "1000007864",
    "securityNameAbbr": "大华股份",
    "holdDate": "2023-08-04 00:00:00",
    "orgCode": "10063640",
    "orgName": "摩根士丹利香港证券有限公司",
    "holdNum": 672500,
    "marketCode": "003",
    "holdSharesRatio": 0.02,
    "holdMarketCap": 14990025,
    "closePrice": 22.29,
    "changeRate": 6.244,
    "holdMarketCapone": 12283605,
    "holdMarketCapfive": 13353225,
    "holdMarketCapten": 11424921,
    "participantCode": "B01274"
  },
  {
    "secucode": "002236.SZ",
    "securityCode": "002236",
    "securityInnerCode": "1000007864",
    "securityNameAbbr": "大华股份",
    "holdDate": "2023-08-03 00:00:00",
    "orgCode": "10063640",
    "orgName": "摩根士丹利香港证券有限公司",
    "holdNum": 129000,
    "marketCode": "003",
    "holdSharesRatio": 0,
    "holdMarketCap": 2706420,
    "closePrice": 20.98,
    "changeRate": -2.8254,
    "holdMarketCapone": -10184969,
    "holdMarketCapfive": 1697905,
    "holdMarketCapten": 2212275,
    "participantCode": "B01274"
  },
  {
    "secucode": "002236.SZ",
    "securityCode": "002236",
    "securityInnerCode": "1000007864",
    "securityNameAbbr": "大华股份",
    "holdDate": "2023-08-02 00:00:00",
    "orgCode": "10063640",
    "orgName": "摩根士丹利香港证券有限公司",
    "holdNum": 597100,
    "marketCode": "003",
    "holdSharesRatio": 0.01,
    "holdMarketCap": 12891389,
    "closePrice": 21.59,
    "changeRate": -0.6443,
    "holdMarketCapone": -8734307,
    "holdMarketCapfive": 11143643,
    "holdMarketCapten": 11085749,
    "participantCode": "B01274"
  },
  {
    "secucode": "002236.SZ",
    "securityCode": "002236",
    "securityInnerCode": "1000007864",
    "securityNameAbbr": "大华股份",
    "holdDate": "2023-08-01 00:00:00",
    "orgCode": "10063640",
    "orgName": "摩根士丹利香港证券有限公司",
    "holdNum": 995200,
    "marketCode": "003",
    "holdSharesRatio": 0.02,
    "holdMarketCap": 21625696,
    "closePrice": 21.73,
    "changeRate": -1.0023,
    "holdMarketCapone": 2213116,
    "holdMarketCapfive": 15098129.2,
    "holdMarketCapten": 21428596,
    "participantCode": "B01274"
  },
  {
    "secucode": "002236.SZ",
    "securityCode": "002236",
    "securityInnerCode": "1000007864",
    "securityNameAbbr": "大华股份",
    "holdDate": "2023-07-31 00:00:00",
    "orgCode": "10063640",
    "orgName": "摩根士丹利香港证券有限公司",
    "holdNum": 884400,
    "marketCode": "003",
    "holdSharesRatio": 0.02,
    "holdMarketCap": 19412580,
    "closePrice": 21.95,
    "changeRate": 7.2825,
    "holdMarketCapone": 17775780,
    "holdMarketCapfive": 16483155,
    "holdMarketCapten": 19172889,
    "participantCode": "B01274"
  },
  {
    "secucode": "002236.SZ",
    "securityCode": "002236",
    "securityInnerCode": "1000007864",
    "securityNameAbbr": "大华股份",
    "holdDate": "2023-07-28 00:00:00",
    "orgCode": "10063640",
    "orgName": "摩根士丹利香港证券有限公司",
    "holdNum": 80000,
    "marketCode": "003",
    "holdSharesRatio": 0,
    "holdMarketCap": 1636800,
    "closePrice": 20.46,
    "changeRate": 2.0449,
    "holdMarketCapone": 628285,
    "holdMarketCapfive": -1928304,
    "holdMarketCapten": -178545,
    "participantCode": "B01274"
  },
  {
    "secucode": "002236.SZ",
    "securityCode": "002236",
    "securityInnerCode": "1000007864",
    "securityNameAbbr": "大华股份",
    "holdDate": "2023-07-27 00:00:00",
    "orgCode": "10063640",
    "orgName": "摩根士丹利香港证券有限公司",
    "holdNum": 50300,
    "marketCode": "003",
    "holdSharesRatio": 0,
    "holdMarketCap": 1008515,
    "closePrice": 20.05,
    "changeRate": -1.5709,
    "holdMarketCapone": -739231,
    "holdMarketCapfive": 514370,
    "holdMarketCapten": -1150813,
    "participantCode": "B01274"
  },
  {
    "secucode": "002236.SZ",
    "securityCode": "002236",
    "securityInnerCode": "1000007864",
    "securityNameAbbr": "大华股份",
    "holdDate": "2023-07-26 00:00:00",
    "orgCode": "10063640",
    "orgName": "摩根士丹利香港证券有限公司",
    "holdNum": 85800,
    "marketCode": "003",
    "holdSharesRatio": 0,
    "holdMarketCap": 1747746,
    "closePrice": 20.37,
    "changeRate": -3.6879,
    "holdMarketCapone": -4779820.8,
    "holdMarketCapfive": -57894,
    "holdMarketCapten": -67331446.6,
    "participantCode": "B01274"
  },
  {
    "secucode": "002236.SZ",
    "securityCode": "002236",
    "securityInnerCode": "1000007864",
    "securityNameAbbr": "大华股份",
    "holdDate": "2023-07-25 00:00:00",
    "orgCode": "10063640",
    "orgName": "摩根士丹利香港证券有限公司",
    "holdNum": 308632,
    "marketCode": "003",
    "holdSharesRatio": 0,
    "holdMarketCap": 6527566.8,
    "closePrice": 21.15,
    "changeRate": 1.4388,
    "holdMarketCapone": 3598141.8,
    "holdMarketCapfive": 6330466.8,
    "holdMarketCapten": -65278062.36,
    "participantCode": "B01274"
  },
  {
    "secucode": "002236.SZ",
    "securityCode": "002236",
    "securityInnerCode": "1000007864",
    "securityNameAbbr": "大华股份",
    "holdDate": "2023-07-24 00:00:00",
    "orgCode": "10063640",
    "orgName": "摩根士丹利香港证券有限公司",
    "holdNum": 140500,
    "marketCode": "003",
    "holdSharesRatio": 0,
    "holdMarketCap": 2929425,
    "closePrice": 20.85,
    "changeRate": 1.4105,
    "holdMarketCapone": -635679,
    "holdMarketCapfive": 2689734,
    "holdMarketCapten": -77690031.64,
    "participantCode": "B01274"
  },
  {
    "secucode": "002236.SZ",
    "securityCode": "002236",
    "securityInnerCode": "1000007864",
    "securityNameAbbr": "大华股份",
    "holdDate": "2023-07-21 00:00:00",
    "orgCode": "10063640",
    "orgName": "摩根士丹利香港证券有限公司",
    "holdNum": 173400,
    "marketCode": "003",
    "holdSharesRatio": 0,
    "holdMarketCap": 3565104,
    "closePrice": 20.56,
    "changeRate": -1.3909,
    "holdMarketCapone": 3070959,
    "holdMarketCapfive": 1749759,
    "holdMarketCapten": -105177624.24,
    "participantCode": "B01274"
  },
  {
    "secucode": "002236.SZ",
    "securityCode": "002236",
    "securityInnerCode": "1000007864",
    "securityNameAbbr": "大华股份",
    "holdDate": "2023-07-20 00:00:00",
    "orgCode": "10063640",
    "orgName": "摩根士丹利香港证券有限公司",
    "holdNum": 23700,
    "marketCode": "003",
    "holdSharesRatio": 0,
    "holdMarketCap": 494145,
    "closePrice": 20.85,
    "changeRate": -5.3134,
    "holdMarketCapone": -1311495,
    "holdMarketCapfive": -1665183,
    "holdMarketCapten": -85293748.44,
    "participantCode": "B01274"
  },
  {
    "secucode": "002236.SZ",
    "securityCode": "002236",
    "securityInnerCode": "1000007864",
    "securityNameAbbr": "大华股份",
    "holdDate": "2023-07-19 00:00:00",
    "orgCode": "10063640",
    "orgName": "摩根士丹利香港证券有限公司",
    "holdNum": 82000,
    "marketCode": "003",
    "holdSharesRatio": 0,
    "holdMarketCap": 1805640,
    "closePrice": 22.02,
    "changeRate": 0.5479,
    "holdMarketCapone": 1608540,
    "holdMarketCapfive": -67273552.6,
    "holdMarketCapten": -55892456.29,
    "participantCode": "B01274"
  },
  {
    "secucode": "002236.SZ",
    "securityCode": "002236",
    "securityInnerCode": "1000007864",
    "securityNameAbbr": "大华股份",
    "holdDate": "2023-07-18 00:00:00",
    "orgCode": "10063640",
    "orgName": "摩根士丹利香港证券有限公司",
    "holdNum": 9000,
    "marketCode": "003",
    "holdSharesRatio": 0,
    "holdMarketCap": 197100,
    "closePrice": 21.9,
    "changeRate": -2.1448,
    "holdMarketCapone": -42591,
    "holdMarketCapfive": -71608529.16,
    "holdMarketCapten": -33087619.65,
    "participantCode": "B01274"
  },
  {
    "secucode": "002236.SZ",
    "securityCode": "002236",
    "securityInnerCode": "1000007864",
    "securityNameAbbr": "大华股份",
    "holdDate": "2023-07-14 00:00:00",
    "orgCode": "10063640",
    "orgName": "摩根士丹利香港证券有限公司",
    "holdNum": 10900,
    "marketCode": "003",
    "holdSharesRatio": 0,
    "holdMarketCap": 239691,
    "closePrice": 21.99,
    "changeRate": -2.2667,
    "holdMarketCapone": -1575654,
    "holdMarketCapfive": -80379765.64,
    "holdMarketCapten": -58840794.75,
    "participantCode": "B01274"
  },
  {
    "secucode": "002236.SZ",
    "securityCode": "002236",
    "securityInnerCode": "1000007864",
    "securityNameAbbr": "大华股份",
    "holdDate": "2023-07-13 00:00:00",
    "orgCode": "10063640",
    "orgName": "摩根士丹利香港证券有限公司",
    "holdNum": 80682,
    "marketCode": "003",
    "holdSharesRatio": 0,
    "holdMarketCap": 1815345,
    "closePrice": 22.5,
    "changeRate": 3.7823,
    "holdMarketCapone": -343983,
    "holdMarketCapfive": -106927383.24,
    "holdMarketCapten": -56929092.41,
    "participantCode": "B01274"
  },
  {
    "secucode": "002236.SZ",
    "securityCode": "002236",
    "securityInnerCode": "1000007864",
    "securityNameAbbr": "大华股份",
    "holdDate": "2023-07-12 00:00:00",
    "orgCode": "10063640",
    "orgName": "摩根士丹利香港证券有限公司",
    "holdNum": 99600,
    "marketCode": "003",
    "holdSharesRatio": 0,
    "holdMarketCap": 2159328,
    "closePrice": 21.68,
    "changeRate": 0.0461,
    "holdMarketCapone": -66919864.6,
    "holdMarketCapfive": -83628565.44,
    "holdMarketCapten": -32594592,
    "participantCode": "B01274"
  },
  {
    "secucode": "002236.SZ",
    "securityCode": "002236",
    "securityInnerCode": "1000007864",
    "securityNameAbbr": "大华股份",
    "holdDate": "2023-07-11 00:00:00",
    "orgCode": "10063640",
    "orgName": "摩根士丹利香港证券有限公司",
    "holdNum": 3187780,
    "marketCode": "003",
    "holdSharesRatio": 0.09,
    "holdMarketCap": 69079192.6,
    "closePrice": 21.67,
    "changeRate": 4.6354,
    "holdMarketCapone": -2726436.56,
    "holdMarketCapfive": 11381096.31,
    "holdMarketCapten": 53335034.55,
    "participantCode": "B01274"
  },
  {
    "secucode": "002236.SZ",
    "securityCode": "002236",
    "securityInnerCode": "1000007864",
    "securityNameAbbr": "大华股份",
    "holdDate": "2023-07-10 00:00:00",
    "orgCode": "10063640",
    "orgName": "摩根士丹利香港证券有限公司",
    "holdNum": 3467196,
    "marketCode": "003",
    "holdSharesRatio": 0.1,
    "holdMarketCap": 71805629.16,
    "closePrice": 20.71,
    "changeRate": -0.6238,
    "holdMarketCapone": -8813827.48,
    "holdMarketCapfive": 38520909.51,
    "holdMarketCapten": 50449242.34,
    "participantCode": "B01274"
  },
  {
    "secucode": "002236.SZ",
    "securityCode": "002236",
    "securityInnerCode": "1000007864",
    "securityNameAbbr": "大华股份",
    "holdDate": "2023-07-07 00:00:00",
    "orgCode": "10063640",
    "orgName": "摩根士丹利香港证券有限公司",
    "holdNum": 3868496,
    "marketCode": "003",
    "holdSharesRatio": 0.11,
    "holdMarketCap": 80619456.64,
    "closePrice": 20.84,
    "changeRate": -3.9189,
    "holdMarketCapone": -28123271.6,
    "holdMarketCapfive": 21538970.89,
    "holdMarketCapten": 59321686.64,
    "participantCode": "B01274"
  },
  {
    "secucode": "002236.SZ",
    "securityCode": "002236",
    "securityInnerCode": "1000007864",
    "securityNameAbbr": "大华股份",
    "holdDate": "2023-07-06 00:00:00",
    "orgCode": "10063640",
    "orgName": "摩根士丹利香港证券有限公司",
    "holdNum": 5013496,
    "marketCode": "003",
    "holdSharesRatio": 0.15,
    "holdMarketCap": 108742728.24,
    "closePrice": 21.69,
    "changeRate": 1.166,
    "holdMarketCapone": 22954834.8,
    "holdMarketCapfive": 49998290.83,
    "holdMarketCapten": -2435504.26,
    "participantCode": "B01274"
  },
  {
    "secucode": "002236.SZ",
    "securityCode": "002236",
    "securityInnerCode": "1000007864",
    "securityNameAbbr": "大华股份",
    "holdDate": "2023-07-05 00:00:00",
    "orgCode": "10063640",
    "orgName": "摩根士丹利香港证券有限公司",
    "holdNum": 4001301,
    "marketCode": "003",
    "holdSharesRatio": 0.12,
    "holdMarketCap": 85787893.44,
    "closePrice": 21.44,
    "changeRate": -0.418,
    "holdMarketCapone": 28089797.15,
    "holdMarketCapfive": 51033973.44,
    "holdMarketCapten": 9223389.14,
    "participantCode": "B01274"
  },
  {
    "secucode": "002236.SZ",
    "securityCode": "002236",
    "securityInnerCode": "1000007864",
    "securityNameAbbr": "大华股份",
    "holdDate": "2023-07-04 00:00:00",
    "orgCode": "10063640",
    "orgName": "摩根士丹利香港证券有限公司",
    "holdNum": 2679893,
    "marketCode": "003",
    "holdSharesRatio": 0.08,
    "holdMarketCap": 57698096.29,
    "closePrice": 21.53,
    "changeRate": 7.9198,
    "holdMarketCapone": 24413376.64,
    "holdMarketCapfive": 41953938.24,
    "holdMarketCapten": -479807097.89,
    "participantCode": "B01274"
  },
  {
    "secucode": "002236.SZ",
    "securityCode": "002236",
    "securityInnerCode": "1000007864",
    "securityNameAbbr": "大华股份",
    "holdDate": "2023-07-03 00:00:00",
    "orgCode": "10063640",
    "orgName": "摩根士丹利香港证券有限公司",
    "holdNum": 1668407,
    "marketCode": "003",
    "holdSharesRatio": 0.05,
    "holdMarketCap": 33284719.65,
    "closePrice": 19.95,
    "changeRate": 1.0127,
    "holdMarketCapone": -25795766.1,
    "holdMarketCapfive": 11928332.83,
    "holdMarketCapten": -492217807.47,
    "participantCode": "B01274"
  },
  {
    "secucode": "002236.SZ",
    "securityCode": "002236",
    "securityInnerCode": "1000007864",
    "securityNameAbbr": "大华股份",
    "holdDate": "2023-06-30 00:00:00",
    "orgCode": "10063640",
    "orgName": "摩根士丹利香港证券有限公司",
    "holdNum": 2991417,
    "marketCode": "003",
    "holdSharesRatio": 0.08,
    "holdMarketCap": 59080485.75,
    "closePrice": 19.75,
    "changeRate": 0.1014,
    "holdMarketCapone": 336048.34,
    "holdMarketCapfive": 37782715.75,
    "holdMarketCapten": -515491057.85,
    "participantCode": "B01274"
  },
  {
    "secucode": "002236.SZ",
    "securityCode": "002236",
    "securityInnerCode": "1000007864",
    "securityNameAbbr": "大华股份",
    "holdDate": "2023-06-29 00:00:00",
    "orgCode": "10063640",
    "orgName": "摩根士丹利香港证券有限公司",
    "holdNum": 2977417,
    "marketCode": "003",
    "holdSharesRatio": 0.08,
    "holdMarketCap": 58744437.41,
    "closePrice": 19.73,
    "changeRate": 2.7604,
    "holdMarketCapone": 23990517.41,
    "holdMarketCapfive": -52433795.09,
    "holdMarketCapten": -517453712.75,
    "participantCode": "B01274"
  },
  {
    "secucode": "002236.SZ",
    "securityCode": "002236",
    "securityInnerCode": "1000007864",
    "securityNameAbbr": "大华股份",
    "holdDate": "2023-06-28 00:00:00",
    "orgCode": "10063640",
    "orgName": "摩根士丹利香港证券有限公司",
    "holdNum": 1810100,
    "marketCode": "003",
    "holdSharesRatio": 0.05,
    "holdMarketCap": 34753920,
    "closePrice": 19.2,
    "changeRate": -8.7886,
    "holdMarketCapone": 19009761.95,
    "holdMarketCapfive": -41810584.3,
    "holdMarketCapten": -514740057.48,
    "participantCode": "B01274"
  },
  {
    "secucode": "002236.SZ",
    "securityCode": "002236",
    "securityInnerCode": "1000007864",
    "securityNameAbbr": "大华股份",
    "holdDate": "2023-06-27 00:00:00",
    "orgCode": "10063640",
    "orgName": "摩根士丹利香港证券有限公司",
    "holdNum": 747941,
    "marketCode": "003",
    "holdSharesRatio": 0.02,
    "holdMarketCap": 15744158.05,
    "closePrice": 21.05,
    "changeRate": -0.3786,
    "holdMarketCapone": -5612228.77,
    "holdMarketCapfive": -521761036.13,
    "holdMarketCapten": -504426798.2,
    "participantCode": "B01274"
  },
  {
    "secucode": "002236.SZ",
    "securityCode": "002236",
    "securityInnerCode": "1000007864",
    "securityNameAbbr": "大华股份",
    "holdDate": "2023-06-26 00:00:00",
    "orgCode": "10063640",
    "orgName": "摩根士丹利香港证券有限公司",
    "holdNum": 1010714,
    "marketCode": "003",
    "holdSharesRatio": 0.03,
    "holdMarketCap": 21356386.82,
    "closePrice": 21.13,
    "changeRate": -4.3891,
    "holdMarketCapone": 58616.82,
    "holdMarketCapfive": -504146140.3,
    "holdMarketCapten": -405426676.46,
    "participantCode": "B01274"
  },
  {
    "secucode": "002236.SZ",
    "securityCode": "002236",
    "securityInnerCode": "1000007864",
    "securityNameAbbr": "大华股份",
    "holdDate": "2023-06-21 00:00:00",
    "orgCode": "10063640",
    "orgName": "摩根士丹利香港证券有限公司",
    "holdNum": 963700,
    "marketCode": "003",
    "holdSharesRatio": 0.02,
    "holdMarketCap": 21297770,
    "closePrice": 22.1,
    "changeRate": -7.0257,
    "holdMarketCapone": -89880462.5,
    "holdMarketCapfive": -553273773.6,
    "holdMarketCapten": -352453594.66,
    "participantCode": "B01274"
  },
  {
    "secucode": "002236.SZ",
    "securityCode": "002236",
    "securityInnerCode": "1000007864",
    "securityNameAbbr": "大华股份",
    "holdDate": "2023-06-20 00:00:00",
    "orgCode": "10063640",
    "orgName": "摩根士丹利香港证券有限公司",
    "holdNum": 4677250,
    "marketCode": "003",
    "holdSharesRatio": 0.14,
    "holdMarketCap": 111178232.5,
    "closePrice": 23.77,
    "changeRate": 2.6782,
    "holdMarketCapone": 34613728.2,
    "holdMarketCapfive": -465019917.66,
    "holdMarketCapten": -259377835.26,
    "participantCode": "B01274"
  },
  {
    "secucode": "002236.SZ",
    "securityCode": "002236",
    "securityInnerCode": "1000007864",
    "securityNameAbbr": "大华股份",
    "holdDate": "2023-06-19 00:00:00",
    "orgCode": "10063640",
    "orgName": "摩根士丹利香港证券有限公司",
    "holdNum": 3307322,
    "marketCode": "003",
    "holdSharesRatio": 0.09,
    "holdMarketCap": 76564504.3,
    "closePrice": 23.15,
    "changeRate": 8.2788,
    "holdMarketCapone": -460940689.88,
    "holdMarketCapfive": -472929473.18,
    "holdMarketCapten": -309640135.25,
    "participantCode": "B01274"
  },
  {
    "secucode": "002236.SZ",
    "securityCode": "002236",
    "securityInnerCode": "1000007864",
    "securityNameAbbr": "大华股份",
    "holdDate": "2023-06-16 00:00:00",
    "orgCode": "10063640",
    "orgName": "摩根士丹利香港证券有限公司",
    "holdNum": 25140561,
    "marketCode": "003",
    "holdSharesRatio": 0.75,
    "holdMarketCap": 537505194.18,
    "closePrice": 21.38,
    "changeRate": 9.9794,
    "holdMarketCapone": 12002667.06,
    "holdMarketCapfive": 17334237.93,
    "holdMarketCapten": 162324862.48,
    "participantCode": "B01274"
  },
  {
    "secucode": "002236.SZ",
    "securityCode": "002236",
    "securityInnerCode": "1000007864",
    "securityNameAbbr": "大华股份",
    "holdDate": "2023-06-15 00:00:00",
    "orgCode": "10063640",
    "orgName": "摩根士丹利香港证券有限公司",
    "holdNum": 27032023,
    "marketCode": "003",
    "holdSharesRatio": 0.81,
    "holdMarketCap": 525502527.12,
    "closePrice": 19.44,
    "changeRate": -4.9389,
    "holdMarketCapone": -49069016.48,
    "holdMarketCapfive": 98719463.84,
    "holdMarketCapten": 137042148.22,
    "participantCode": "B01274"
  },
  {
    "secucode": "002236.SZ",
    "securityCode": "002236",
    "securityInnerCode": "1000007864",
    "securityNameAbbr": "大华股份",
    "holdDate": "2023-06-14 00:00:00",
    "orgCode": "10063640",
    "orgName": "摩根士丹利香港证券有限公司",
    "holdNum": 28096408,
    "marketCode": "003",
    "holdSharesRatio": 0.84,
    "holdMarketCap": 574571543.6,
    "closePrice": 20.45,
    "changeRate": 1.8426,
    "holdMarketCapone": -1626606.56,
    "holdMarketCapfive": 200820178.94,
    "holdMarketCapten": 203422679.6,
    "participantCode": "B01274"
  },
  {
    "secucode": "002236.SZ",
    "securityCode": "002236",
    "securityInnerCode": "1000007864",
    "securityNameAbbr": "大华股份",
    "holdDate": "2023-06-13 00:00:00",
    "orgCode": "10063640",
    "orgName": "摩根士丹利香港证券有限公司",
    "holdNum": 28695127,
    "marketCode": "003",
    "holdSharesRatio": 0.86,
    "holdMarketCap": 576198150.16,
    "closePrice": 20.08,
    "changeRate": 6.5817,
    "holdMarketCapone": 26704172.68,
    "holdMarketCapfive": 205642082.4,
    "holdMarketCapten": 188460253.8,
    "participantCode": "B01274"
  },
  {
    "secucode": "002236.SZ",
    "securityCode": "002236",
    "securityInnerCode": "1000007864",
    "securityNameAbbr": "大华股份",
    "holdDate": "2023-06-12 00:00:00",
    "orgCode": "10063640",
    "orgName": "摩根士丹利香港证券有限公司",
    "holdNum": 29166347,
    "marketCode": "003",
    "holdSharesRatio": 0.87,
    "holdMarketCap": 549493977.48,
    "closePrice": 18.84,
    "changeRate": 0.48,
    "holdMarketCapone": 29323021.23,
    "holdMarketCapfive": 163289337.93,
    "holdMarketCapten": 254586914.28,
    "participantCode": "B01274"
  },
  {
    "secucode": "002236.SZ",
    "securityCode": "002236",
    "securityInnerCode": "1000007864",
    "securityNameAbbr": "大华股份",
    "holdDate": "2023-06-09 00:00:00",
    "orgCode": "10063640",
    "orgName": "摩根士丹利香港证券有限公司",
    "holdNum": 27742451,
    "marketCode": "003",
    "holdSharesRatio": 0.83,
    "holdMarketCap": 520170956.25,
    "closePrice": 18.75,
    "changeRate": -2.749,
    "holdMarketCapone": 93387892.97,
    "holdMarketCapfive": 144990624.55,
    "holdMarketCapten": 367775240.78,
    "participantCode": "B01274"
  },
  {
    "secucode": "002236.SZ",
    "securityCode": "002236",
    "securityInnerCode": "1000007864",
    "securityNameAbbr": "大华股份",
    "holdDate": "2023-06-08 00:00:00",
    "orgCode": "10063640",
    "orgName": "摩根士丹利香港证券有限公司",
    "holdNum": 22136051,
    "marketCode": "003",
    "holdSharesRatio": 0.66,
    "holdMarketCap": 426783063.28,
    "closePrice": 19.28,
    "changeRate": -1.9329,
    "holdMarketCapone": 53031698.62,
    "holdMarketCapfive": 38322684.38,
    "holdMarketCapten": 301779110.95,
    "participantCode": "B01274"
  },
  {
    "secucode": "002236.SZ",
    "securityCode": "002236",
    "securityInnerCode": "1000007864",
    "securityNameAbbr": "大华股份",
    "holdDate": "2023-06-07 00:00:00",
    "orgCode": "10063640",
    "orgName": "摩根士丹利香港证券有限公司",
    "holdNum": 19010751,
    "marketCode": "003",
    "holdSharesRatio": 0.57,
    "holdMarketCap": 373751364.66,
    "closePrice": 19.66,
    "changeRate": -0.8073,
    "holdMarketCapone": 3195296.9,
    "holdMarketCapfive": 2602500.66,
    "holdMarketCapten": 287072566.66,
    "participantCode": "B01274"
  },
  {
    "secucode": "002236.SZ",
    "securityCode": "002236",
    "securityInnerCode": "1000007864",
    "securityNameAbbr": "大华股份",
    "holdDate": "2023-06-06 00:00:00",
    "orgCode": "10063640",
    "orgName": "摩根士丹利香港证券有限公司",
    "holdNum": 18696068,
    "marketCode": "003",
    "holdSharesRatio": 0.56,
    "holdMarketCap": 370556067.76,
    "closePrice": 19.82,
    "changeRate": -4.2974,
    "holdMarketCapone": -15648571.79,
    "holdMarketCapfive": -17181828.6,
    "holdMarketCapten": 275895335.44,
    "participantCode": "B01274"
  },
  {
    "secucode": "002236.SZ",
    "securityCode": "002236",
    "securityInnerCode": "1000007864",
    "securityNameAbbr": "大华股份",
    "holdDate": "2023-06-05 00:00:00",
    "orgCode": "10063640",
    "orgName": "摩根士丹利香港证券有限公司",
    "holdNum": 18434589,
    "marketCode": "003",
    "holdSharesRatio": 0.55,
    "holdMarketCap": 386204639.55,
    "closePrice": 20.95,
    "changeRate": 1.4037,
    "holdMarketCapone": 11024307.85,
    "holdMarketCapfive": 91297576.35,
    "holdMarketCapten": 296807579.07,
    "participantCode": "B01274"
  },
  {
    "secucode": "002236.SZ",
    "securityCode": "002236",
    "securityInnerCode": "1000007864",
    "securityNameAbbr": "大华股份",
    "holdDate": "2023-06-02 00:00:00",
    "orgCode": "10063640",
    "orgName": "摩根士丹利香港证券有限公司",
    "holdNum": 18159745,
    "marketCode": "003",
    "holdSharesRatio": 0.54,
    "holdMarketCap": 375180331.7,
    "closePrice": 20.66,
    "changeRate": -1.1483,
    "holdMarketCapone": -13280047.2,
    "holdMarketCapfive": 222784616.23,
    "holdMarketCapten": 275009857.14,
    "participantCode": "B01274"
  }
]