[
  {
    "secucode": "003001.SZ",
    "securityCode": "003001",
    "orgCode": "10493881",
    "endDate": "2023-01-30 00:00:00",
    "holderName": "MORGAN STANLEY & CO. INTERNATIONAL PLC.",
    "holdNum": 357728,
    "freeHoldnumRatio": 0.725253095952,
    "holdNumChange": "6000",
    "changeRatio": 1.70586362,
    "isHoldorg": "1",
    "holderRank": 5,
    "securityNameAbbr": "中岩大地",
    "holderCode": "10000303290",
    "securityTypeCode": "058001001",
    "holderState": "加仓",
    "holderMarketCap": 5519743.04,
    "holdRatio": 0.28,
    "holdChange": "6000",
    "holdRatioChange": 0.0047,
    "holderType": "QFII",
    "sharesType": "A股",
    "updateDate": "2023-02-07 00:00:00",
    "reportDateName": "2023-01-30",
    "holderNew": "10000303290",
    "freeRatioQoq": "1.70586362",
    "holderStatee": "加仓",
    "isReport": "0",
    "holderCodeOld": "81282466",
    "holderNewtype": "QFII",
    "holdnumChangeName": "增加",
    "isMaxReportdate": "0",
    "cooperationHolderMark": "10000303290",
    "mxid": "e85ae7ae80752707ee167416d8af5e76",
    "listingState": "0",
    "xzchange": 6000,
    "newChangeRatio": "1.70586362"
  }
]