[
  {
    "secucode": "603233.SH",
    "securityCode": "603233",
    "orgCode": "10500736",
    "endDate": "2017-12-31 00:00:00",
    "holderName": "科威特政府投资局-自有资金",
    "holdNum": 1170751,
    "freeHoldnumRatio": 2.926145963509,
    "holdNumChange": "不变",
    "changeRatio": null,
    "isHoldorg": "1",
    "holderRank": 5,
    "securityNameAbbr": "大参林",
    "holderCode": "10199707",
    "securityTypeCode": "058001001",
    "holderState": null,
    "holderMarketCap": 60480996.66,
    "holdRatio": 0.2927,
    "holdChange": "不变",
    "holdRatioChange": 0,
    "holderType": "QFII",
    "sharesType": "A股",
    "updateDate": "2018-04-27 00:00:00",
    "reportDateName": "2017年报",
    "holderNew": "10199707",
    "freeRatioQoq": "不变",
    "holderStatee": null,
    "isReport": "1",
    "holderCodeOld": "80195934",
    "holderNewtype": "QFII",
    "holdnumChangeName": "不变",
    "isMaxReportdate": "0",
    "cooperationHolderMark": "10199707",
    "mxid": "d33012aea58bfc613448ce59930f508d",
    "listingState": "0",
    "xzchange": 0,
    "newChangeRatio": "不变"
  },
  {
    "secucode": "002292.SZ",
    "securityCode": "002292",
    "orgCode": "10110822",
    "endDate": "2017-12-31 00:00:00",
    "holderName": "科威特政府投资局",
    "holdNum": 10939754,
    "freeHoldnumRatio": 1.439230570772,
    "holdNumChange": "5911875",
    "changeRatio": 117.58188691,
    "isHoldorg": "1",
    "holderRank": 5,
    "securityNameAbbr": "奥飞娱乐",
    "holderCode": "10199707",
    "securityTypeCode": "058001001",
    "holderState": "加仓",
    "holderMarketCap": 156329084.66,
    "holdRatio": 0.837,
    "holdChange": "5911875",
    "holdRatioChange": 0.4523,
    "holderType": "QFII",
    "sharesType": "A股",
    "updateDate": "2018-04-27 00:00:00",
    "reportDateName": "2017年报",
    "holderNew": "10199707",
    "freeRatioQoq": "117.59894198",
    "holderStatee": "加仓",
    "isReport": "1",
    "holderCodeOld": "80195934",
    "holderNewtype": "QFII",
    "holdnumChangeName": "增加",
    "isMaxReportdate": "0",
    "cooperationHolderMark": "10199707",
    "mxid": "edc499208c800cea90d255005f72e1e1",
    "listingState": "0",
    "xzchange": 5911875,
    "newChangeRatio": "117.58188691"
  },
  {
    "secucode": "002570.SZ",
    "securityCode": "002570",
    "orgCode": "10058755",
    "endDate": "2017-12-31 00:00:00",
    "holderName": "科威特政府投资局",
    "holdNum": 5748847,
    "freeHoldnumRatio": 0.56240642774,
    "holdNumChange": "不变",
    "changeRatio": null,
    "isHoldorg": "1",
    "holderRank": 8,
    "securityNameAbbr": "贝因美",
    "holderCode": "10199707",
    "securityTypeCode": "058001001",
    "holderState": null,
    "holderMarketCap": 41391698.4,
    "holdRatio": 0.5622,
    "holdChange": "不变",
    "holdRatioChange": 0,
    "holderType": "QFII",
    "sharesType": "A股",
    "updateDate": "2018-04-26 00:00:00",
    "reportDateName": "2017年报",
    "holderNew": "10199707",
    "freeRatioQoq": "0.00943222",
    "holderStatee": null,
    "isReport": "1",
    "holderCodeOld": "80195934",
    "holderNewtype": "QFII",
    "holdnumChangeName": "不变",
    "isMaxReportdate": "0",
    "cooperationHolderMark": "10199707",
    "mxid": "75c363a3a84e28bb8fa7eb27c700cb79",
    "listingState": "0",
    "xzchange": 0,
    "newChangeRatio": "不变"
  },
  {
    "secucode": "600820.SH",
    "securityCode": "600820",
    "orgCode": "10004264",
    "endDate": "2017-12-31 00:00:00",
    "holderName": "科威特政府投资局-自有资金",
    "holdNum": 7762000,
    "freeHoldnumRatio": 0.246875406092,
    "holdNumChange": "新进",
    "changeRatio": null,
    "isHoldorg": "1",
    "holderRank": 10,
    "securityNameAbbr": "隧道股份",
    "holderCode": "10199707",
    "securityTypeCode": "058001001",
    "holderState": "新进",
    "holderMarketCap": 64890320,
    "holdRatio": 0.2469,
    "holdChange": "新进",
    "holdRatioChange": null,
    "holderType": "QFII",
    "sharesType": "A股",
    "updateDate": "2018-04-19 00:00:00",
    "reportDateName": "2017年报",
    "holderNew": "10199707",
    "freeRatioQoq": "新进",
    "holderStatee": "新进",
    "isReport": "1",
    "holderCodeOld": "80195934",
    "holderNewtype": "QFII",
    "holdnumChangeName": "新进",
    "isMaxReportdate": "0",
    "cooperationHolderMark": "10199707",
    "mxid": "a34970c4f1c0f89bc5be15f5aee70fc2",
    "listingState": "0",
    "xzchange": null,
    "newChangeRatio": "新进"
  },
  {
    "secucode": "900942.SH",
    "securityCode": "900942",
    "orgCode": "10002278",
    "endDate": "2017-12-31 00:00:00",
    "holderName": "科威特政府投资局-自有资金",
    "holdNum": 10212938,
    "freeHoldnumRatio": 1.366644988626,
    "holdNumChange": "不变",
    "changeRatio": null,
    "isHoldorg": "1",
    "holderRank": 4,
    "securityNameAbbr": "黄山B股",
    "holderCode": "10199707",
    "securityTypeCode": "058001002",
    "holderState": null,
    "holderMarketCap": 13920234.494,
    "holdRatio": 1.3666,
    "holdChange": "不变",
    "holdRatioChange": 0,
    "holderType": "QFII",
    "sharesType": "A股",
    "updateDate": "2018-04-12 00:00:00",
    "reportDateName": "2017年报",
    "holderNew": "10199707",
    "freeRatioQoq": "不变",
    "holderStatee": null,
    "isReport": "1",
    "holderCodeOld": "80195934",
    "holderNewtype": "QFII",
    "holdnumChangeName": "不变",
    "isMaxReportdate": "0",
    "cooperationHolderMark": "10199707",
    "mxid": "d892f13c57cbec997d89e6cf7302e1a2",
    "listingState": "0",
    "xzchange": 0,
    "newChangeRatio": "不变"
  },
  {
    "secucode": "600479.SH",
    "securityCode": "600479",
    "orgCode": "10007187",
    "endDate": "2017-12-31 00:00:00",
    "holderName": "科威特政府投资局-自有资金",
    "holdNum": 4112654,
    "freeHoldnumRatio": 1.349210942093,
    "holdNumChange": "不变",
    "changeRatio": null,
    "isHoldorg": "1",
    "holderRank": 9,
    "securityNameAbbr": "千金药业",
    "holderCode": "10199707",
    "securityTypeCode": "058001001",
    "holderState": null,
    "holderMarketCap": 57659409.08,
    "holdRatio": 1.1792,
    "holdChange": "不变",
    "holdRatioChange": 0,
    "holderType": "QFII",
    "sharesType": "A股",
    "updateDate": "2018-04-12 00:00:00",
    "reportDateName": "2017年报",
    "holderNew": "10199707",
    "freeRatioQoq": "不变",
    "holderStatee": null,
    "isReport": "1",
    "holderCodeOld": "80195934",
    "holderNewtype": "QFII",
    "holdnumChangeName": "不变",
    "isMaxReportdate": "0",
    "cooperationHolderMark": "10199707",
    "mxid": "99b9fce51b8534bf5bb79282c0d73765",
    "listingState": "0",
    "xzchange": 0,
    "newChangeRatio": "不变"
  },
  {
    "secucode": "600054.SH",
    "securityCode": "600054",
    "orgCode": "10002278",
    "endDate": "2017-12-31 00:00:00",
    "holderName": "科威特政府投资局-自有资金",
    "holdNum": 10212938,
    "freeHoldnumRatio": 1.366644988626,
    "holdNumChange": "不变",
    "changeRatio": null,
    "isHoldorg": "1",
    "holderRank": 4,
    "securityNameAbbr": "黄山旅游",
    "holderCode": "10199707",
    "securityTypeCode": "058001001",
    "holderState": null,
    "holderMarketCap": 145738625.26,
    "holdRatio": 1.3666,
    "holdChange": "不变",
    "holdRatioChange": 0,
    "holderType": "QFII",
    "sharesType": "A股",
    "updateDate": "2018-04-12 00:00:00",
    "reportDateName": "2017年报",
    "holderNew": "10199707",
    "freeRatioQoq": "不变",
    "holderStatee": null,
    "isReport": "1",
    "holderCodeOld": "80195934",
    "holderNewtype": "QFII",
    "holdnumChangeName": "不变",
    "isMaxReportdate": "0",
    "cooperationHolderMark": "10199707",
    "mxid": "44144be0238d87746b7c5699c69c07d3",
    "listingState": "0",
    "xzchange": 0,
    "newChangeRatio": "不变"
  },
  {
    "secucode": "603708.SH",
    "securityCode": "603708",
    "orgCode": "10307141",
    "endDate": "2017-12-31 00:00:00",
    "holderName": "科威特政府投资局-自有资金",
    "holdNum": 1956955,
    "freeHoldnumRatio": 1.246699236908,
    "holdNumChange": "新进",
    "changeRatio": null,
    "isHoldorg": "1",
    "holderRank": 8,
    "securityNameAbbr": "家家悦",
    "holderCode": "10199707",
    "securityTypeCode": "058001001",
    "holderState": "新进",
    "holderMarketCap": 39178239.1,
    "holdRatio": 0.4182,
    "holdChange": "新进",
    "holdRatioChange": null,
    "holderType": "QFII",
    "sharesType": "A股",
    "updateDate": "2018-04-10 00:00:00",
    "reportDateName": "2017年报",
    "holderNew": "10199707",
    "freeRatioQoq": "新进",
    "holderStatee": "新进",
    "isReport": "1",
    "holderCodeOld": "80195934",
    "holderNewtype": "QFII",
    "holdnumChangeName": "新进",
    "isMaxReportdate": "0",
    "cooperationHolderMark": "10199707",
    "mxid": "3d9364c86501d751b36c0f210e6d1145",
    "listingState": "0",
    "xzchange": null,
    "newChangeRatio": "新进"
  },
  {
    "secucode": "002043.SZ",
    "securityCode": "002043",
    "orgCode": "10007291",
    "endDate": "2017-12-31 00:00:00",
    "holderName": "科威特政府投资局",
    "holdNum": 11217447,
    "freeHoldnumRatio": 1.565926042154,
    "holdNumChange": "3217600",
    "changeRatio": 40.22076922,
    "isHoldorg": "1",
    "holderRank": 5,
    "securityNameAbbr": "兔宝宝",
    "holderCode": "10199707",
    "securityTypeCode": "058001001",
    "holderState": "加仓",
    "holderMarketCap": 137525900.22,
    "holdRatio": 1.3006,
    "holdChange": "3217600",
    "holdRatioChange": 0.3715,
    "holderType": "QFII",
    "sharesType": "A股",
    "updateDate": "2018-04-10 00:00:00",
    "reportDateName": "2017年报",
    "holderNew": "10199707",
    "freeRatioQoq": "40.22076922",
    "holderStatee": "加仓",
    "isReport": "1",
    "holderCodeOld": "80195934",
    "holderNewtype": "QFII",
    "holdnumChangeName": "增加",
    "isMaxReportdate": "0",
    "cooperationHolderMark": "10199707",
    "mxid": "91e768ca6686b2325d801899df2b3f44",
    "listingState": "0",
    "xzchange": 3217600,
    "newChangeRatio": "40.22076922"
  },
  {
    "secucode": "600563.SH",
    "securityCode": "600563",
    "orgCode": "10002630",
    "endDate": "2017-12-31 00:00:00",
    "holderName": "科威特政府投资局-自有资金",
    "holdNum": 1711104,
    "freeHoldnumRatio": 0.760490666667,
    "holdNumChange": "新进",
    "changeRatio": null,
    "isHoldorg": "1",
    "holderRank": 7,
    "securityNameAbbr": "法拉电子",
    "holderCode": "10199707",
    "securityTypeCode": "058001001",
    "holderState": "新进",
    "holderMarketCap": 86941194.24,
    "holdRatio": 0.7605,
    "holdChange": "新进",
    "holdRatioChange": null,
    "holderType": "QFII",
    "sharesType": "A股",
    "updateDate": "2018-04-04 00:00:00",
    "reportDateName": "2017年报",
    "holderNew": "10199707",
    "freeRatioQoq": "新进",
    "holderStatee": "新进",
    "isReport": "1",
    "holderCodeOld": "80195934",
    "holderNewtype": "QFII",
    "holdnumChangeName": "新进",
    "isMaxReportdate": "0",
    "cooperationHolderMark": "10199707",
    "mxid": "c2e4b8db120f0feae810b42de6c8485a",
    "listingState": "0",
    "xzchange": null,
    "newChangeRatio": "新进"
  },
  {
    "secucode": "002368.SZ",
    "securityCode": "002368",
    "orgCode": "10135474",
    "endDate": "2017-12-31 00:00:00",
    "holderName": "科威特政府投资局",
    "holdNum": 5637530,
    "freeHoldnumRatio": 1.407758326985,
    "holdNumChange": "1247130",
    "changeRatio": 28.40584001,
    "isHoldorg": "1",
    "holderRank": 6,
    "securityNameAbbr": "太极股份",
    "holderCode": "10199707",
    "securityTypeCode": "058001001",
    "holderState": "加仓",
    "holderMarketCap": 143024136.1,
    "holdRatio": 1.3577,
    "holdChange": "1247130",
    "holdRatioChange": 0.3013,
    "holderType": "QFII",
    "sharesType": "A股",
    "updateDate": "2018-03-31 00:00:00",
    "reportDateName": "2017年报",
    "holderNew": "10199707",
    "freeRatioQoq": "25.62018179",
    "holderStatee": "加仓",
    "isReport": "1",
    "holderCodeOld": "80195934",
    "holderNewtype": "QFII",
    "holdnumChangeName": "增加",
    "isMaxReportdate": "0",
    "cooperationHolderMark": "10199707",
    "mxid": "597f47555cef704c6ed86a755c17de15",
    "listingState": "0",
    "xzchange": 1247130,
    "newChangeRatio": "28.40584001"
  },
  {
    "secucode": "600125.SH",
    "securityCode": "600125",
    "orgCode": "10002347",
    "endDate": "2017-12-31 00:00:00",
    "holderName": "科威特政府投资局-自有资金",
    "holdNum": 15211491,
    "freeHoldnumRatio": 1.165165540535,
    "holdNumChange": "2745100",
    "changeRatio": 22.02000563,
    "isHoldorg": "1",
    "holderRank": 5,
    "securityNameAbbr": "铁龙物流",
    "holderCode": "10199707",
    "securityTypeCode": "058001001",
    "holderState": "加仓",
    "holderMarketCap": 164588332.62,
    "holdRatio": 1.1652,
    "holdChange": "2745100",
    "holdRatioChange": 0.2103,
    "holderType": "QFII",
    "sharesType": "A股",
    "updateDate": "2018-03-30 00:00:00",
    "reportDateName": "2017年报",
    "holderNew": "10199707",
    "freeRatioQoq": "22.02000563",
    "holderStatee": "加仓",
    "isReport": "1",
    "holderCodeOld": "80195934",
    "holderNewtype": "QFII",
    "holdnumChangeName": "增加",
    "isMaxReportdate": "0",
    "cooperationHolderMark": "10199707",
    "mxid": "66e44eb792d319a9649d67bae8b144d1",
    "listingState": "0",
    "xzchange": 2745100,
    "newChangeRatio": "22.02000563"
  },
  {
    "secucode": "002643.SZ",
    "securityCode": "002643",
    "orgCode": "10031660",
    "endDate": "2017-12-31 00:00:00",
    "holderName": "科威特政府投资局",
    "holdNum": 7801559,
    "freeHoldnumRatio": 0.933282648029,
    "holdNumChange": "不变",
    "changeRatio": null,
    "isHoldorg": "1",
    "holderRank": 6,
    "securityNameAbbr": "万润股份",
    "holderCode": "10199707",
    "securityTypeCode": "058001001",
    "holderState": null,
    "holderMarketCap": 83398665.71,
    "holdRatio": 0.8581,
    "holdChange": "不变",
    "holdRatioChange": 0,
    "holderType": "QFII",
    "sharesType": "A股",
    "updateDate": "2018-03-29 00:00:00",
    "reportDateName": "2017年报",
    "holderNew": "10199707",
    "freeRatioQoq": "-2.02854624",
    "holderStatee": null,
    "isReport": "1",
    "holderCodeOld": "80195934",
    "holderNewtype": "QFII",
    "holdnumChangeName": "不变",
    "isMaxReportdate": "0",
    "cooperationHolderMark": "10199707",
    "mxid": "42d18406e110ede80f278eb27bb93887",
    "listingState": "0",
    "xzchange": 0,
    "newChangeRatio": "不变"
  },
  {
    "secucode": "002206.SZ",
    "securityCode": "002206",
    "orgCode": "10052380",
    "endDate": "2017-12-31 00:00:00",
    "holderName": "科威特政府投资局",
    "holdNum": 11978888,
    "freeHoldnumRatio": 1.260858890855,
    "holdNumChange": "新进",
    "changeRatio": null,
    "isHoldorg": "1",
    "holderRank": 9,
    "securityNameAbbr": "海利得",
    "holderCode": "10199707",
    "securityTypeCode": "058001001",
    "holderState": "新进",
    "holderMarketCap": 71034805.84,
    "holdRatio": 0.9794,
    "holdChange": "新进",
    "holdRatioChange": null,
    "holderType": "QFII",
    "sharesType": "A股",
    "updateDate": "2018-03-20 00:00:00",
    "reportDateName": "2017年报",
    "holderNew": "10199707",
    "freeRatioQoq": "新进",
    "holderStatee": "新进",
    "isReport": "1",
    "holderCodeOld": "80195934",
    "holderNewtype": "QFII",
    "holdnumChangeName": "新进",
    "isMaxReportdate": "0",
    "cooperationHolderMark": "10199707",
    "mxid": "c6a28e7759e9881b2e463349afd62a4a",
    "listingState": "0",
    "xzchange": null,
    "newChangeRatio": "新进"
  },
  {
    "secucode": "600308.SH",
    "securityCode": "600308",
    "orgCode": "10002502",
    "endDate": "2017-12-31 00:00:00",
    "holderName": "科威特政府投资局-自有资金",
    "holdNum": 6439417,
    "freeHoldnumRatio": 0.551527045619,
    "holdNumChange": "新进",
    "changeRatio": null,
    "isHoldorg": "1",
    "holderRank": 9,
    "securityNameAbbr": "华泰股份",
    "holderCode": "10199707",
    "securityTypeCode": "058001001",
    "holderState": "新进",
    "holderMarketCap": 40439538.76,
    "holdRatio": 0.5515,
    "holdChange": "新进",
    "holdRatioChange": null,
    "holderType": "QFII",
    "sharesType": "A股",
    "updateDate": "2018-03-17 00:00:00",
    "reportDateName": "2017年报",
    "holderNew": "10199707",
    "freeRatioQoq": "新进",
    "holderStatee": "新进",
    "isReport": "1",
    "holderCodeOld": "80195934",
    "holderNewtype": "QFII",
    "holdnumChangeName": "新进",
    "isMaxReportdate": "0",
    "cooperationHolderMark": "10199707",
    "mxid": "34493b3b32fc370d057ec2727f7cb6ba",
    "listingState": "0",
    "xzchange": null,
    "newChangeRatio": "新进"
  },
  {
    "secucode": "002419.SZ",
    "securityCode": "002419",
    "orgCode": "10127032",
    "endDate": "2017-12-31 00:00:00",
    "holderName": "科威特政府投资局",
    "holdNum": 7074964,
    "freeHoldnumRatio": 0.88444716388,
    "holdNumChange": "新进",
    "changeRatio": null,
    "isHoldorg": "1",
    "holderRank": 5,
    "securityNameAbbr": "天虹股份",
    "holderCode": "10199707",
    "securityTypeCode": "058001001",
    "holderState": "新进",
    "holderMarketCap": 107963950.64,
    "holdRatio": 0.8841,
    "holdChange": "新进",
    "holdRatioChange": null,
    "holderType": "QFII",
    "sharesType": "A股",
    "updateDate": "2018-03-15 00:00:00",
    "reportDateName": "2017年报",
    "holderNew": "10199707",
    "freeRatioQoq": "新进",
    "holderStatee": "新进",
    "isReport": "1",
    "holderCodeOld": "80195934",
    "holderNewtype": "QFII",
    "holdnumChangeName": "新进",
    "isMaxReportdate": "0",
    "cooperationHolderMark": "10199707",
    "mxid": "83b3e9df2f0a5f00c0c5a12f2f0f3a08",
    "listingState": "0",
    "xzchange": null,
    "newChangeRatio": "新进"
  },
  {
    "secucode": "300146.SZ",
    "securityCode": "300146",
    "orgCode": "10157500",
    "endDate": "2017-12-31 00:00:00",
    "holderName": "科威特政府投资局",
    "holdNum": 5600408,
    "freeHoldnumRatio": 0.642766653972,
    "holdNumChange": "新进",
    "changeRatio": null,
    "isHoldorg": "1",
    "holderRank": 10,
    "securityNameAbbr": "汤臣倍健",
    "holderCode": "10199707",
    "securityTypeCode": "058001001",
    "holderState": "新进",
    "holderMarketCap": 84118128.16,
    "holdRatio": 0.3809,
    "holdChange": "新进",
    "holdRatioChange": null,
    "holderType": "QFII",
    "sharesType": "A股",
    "updateDate": "2018-02-28 00:00:00",
    "reportDateName": "2017年报",
    "holderNew": "10199707",
    "freeRatioQoq": "新进",
    "holderStatee": "新进",
    "isReport": "1",
    "holderCodeOld": "80195934",
    "holderNewtype": "QFII",
    "holdnumChangeName": "新进",
    "isMaxReportdate": "0",
    "cooperationHolderMark": "10199707",
    "mxid": "f6710f3fd40edb36a0e275243166712a",
    "listingState": "0",
    "xzchange": null,
    "newChangeRatio": "新进"
  }
]